CHANGES.rst
CONTRIBUTORS.rst
MANIFEST.in
README.rst
setup.cfg
setup.py
docs/LICENSE.GPL
docs/LICENSE.rst
docs/index.rst
src/collective/__init__.py
src/collective.eeatags.collection.egg-info/PKG-INFO
src/collective.eeatags.collection.egg-info/SOURCES.txt
src/collective.eeatags.collection.egg-info/dependency_links.txt
src/collective.eeatags.collection.egg-info/entry_points.txt
src/collective.eeatags.collection.egg-info/namespace_packages.txt
src/collective.eeatags.collection.egg-info/not-zip-safe
src/collective.eeatags.collection.egg-info/requires.txt
src/collective.eeatags.collection.egg-info/top_level.txt
src/collective/eeatags/__init__.py
src/collective/eeatags/collection/__init__.py
src/collective/eeatags/collection/configure.zcml
src/collective/eeatags/collection/interfaces.py
src/collective/eeatags/collection/setuphandlers.py
src/collective/eeatags/collection/testing.py
src/collective/eeatags/collection/browser/__init__.py
src/collective/eeatags/collection/browser/configure.zcml
src/collective/eeatags/collection/browser/overrides/.gitkeep
src/collective/eeatags/collection/browser/static/.gitkeep
src/collective/eeatags/collection/locales/collective.eeatags.collection.pot
src/collective/eeatags/collection/locales/update.sh
src/collective/eeatags/collection/profiles/default/browserlayer.xml
src/collective/eeatags/collection/profiles/default/metadata.xml
src/collective/eeatags/collection/profiles/default/registry.xml
src/collective/eeatags/collection/profiles/default/skins.xml
src/collective/eeatags/collection/profiles/uninstall/browserlayer.xml
src/collective/eeatags/collection/skins/eeatags_collection/criterion_edit_form.cpt
src/collective/eeatags/collection/skins/eeatags_collection/criterion_edit_form.cpt.metadata
src/collective/eeatags/collection/tests/__init__.py
src/collective/eeatags/collection/tests/test_robot.py
src/collective/eeatags/collection/tests/test_setup.py
src/collective/eeatags/collection/tests/robot/test_example.robot