Metadata-Version: 1.1
Name: collective.eeatags.collection
Version: 1.0a1
Summary: Eea.tags autocomplet for collection subject/tags criteria
Home-page: https://pypi.python.org/pypi/collective.eeatags.collection
Author: Godefroid Chapelle
Author-email: gotcha@bubblenet.be
License: GPL version 2
Keywords: Python Plone
Platform: UNKNOWN
Classifier: Environment :: Web Environment
Classifier: Framework :: Plone
Classifier: Framework :: Plone :: 4.3
Classifier: Programming Language :: Python
Classifier: Programming Language :: Python :: 2.7
Classifier: Operating System :: OS Independent
Classifier: License :: OSI Approved :: GNU General Public License v2 (GPLv2)
